{
	"deliverableTargetInputFields": [
		{
			"name": "name",
			"id": "name",
			"dataTestId": "createDeliverableTargetName",
			"testId": "createDeliverableTargetNameInput",
			"label": "Name",
			"size": 6
		},
		{
			"name": "target_value",
			"id": "deliverableTotalTargetAmount",
			"dataTestId": "createDeliverableTotalTargetAmount",
			"testId": "createDeliverableTotalTargetAmountInput",
			"label": "Target",
			"size": 6
		},
		{
			"name": "deliverable_category_org",
			"label": "Choose Deliverable category",
			"size": 12,
			"testId": "createDeliverableCategoryOption",
			"dataTestId": "createDeliverableCategory",
			"optionsArray": [],
			"inputLabelId": "demo-simple-select-outlined-label",
			"selectLabelId": "demo-simple-select-outlined-label",
			"selectId": "demo-simple-select-outlined-2",
			"inputType": "select",
			"multiple": true
		}
	],
	"deliverableTracklineInputFields": [
		{
			"name": "reporting_date",
			"id": "Date",
			"dataTestId": "createDeliverableTargetDate",
			"testId": "createDeliverableTargetDateInput",
			"label": "Date",
			"size": 6,
			"type": "date"
		},
		{
			"name": "note",
			"id": "deliverableNote",
			"dataTestId": "createDeliverableNote",
			"testId": "createDeliverableNoteInput",
			"label": "Note",
			"size": 6
		},
		{
			"name": "value",
			"id": "deliverableTotalValue",
			"dataTestId": "createDeliverableTotalValue",
			"testId": "createDeliverableTotalValueInput",
			"label": "Achieved",
			"size": 6
		},
		{
			"name": "annual_year",
			"label": "Choose Annual Year",
			"size": 12,
			"testId": "createAnnualYearOption",
			"dataTestId": "createAnnualYear",
			"optionsArray": [],
			"inputLabelId": "demo-simple-select-outlined-label",
			"selectLabelId": "demo-simple-select-outlined-label",
			"selectId": "demo-simple-select-outlined-2",
			"inputType": "select",
			"multiple": true
		},
		{
			"name": "financial_year",
			"label": "Choose Financial Year",
			"size": 12,
			"testId": "createFinancialYearOption",
			"dataTestId": "createFinancialYear",
			"optionsArray": [],
			"inputLabelId": "demo-simple-select-outlined-label",
			"selectLabelId": "demo-simple-select-outlined-label",
			"selectId": "demo-simple-select-outlined-2",
			"inputType": "select",
			"multiple": true
		}
	]
}
